{
  "nodes": [
    {
      "id": "file:tools/real-transaction-smoke.mjs",
      "type": "file",
      "name": "real-transaction-smoke.mjs",
      "summary": "Source file tools/real-transaction-smoke.mjs containing 17 function(s).",
      "tags": [
        "code",
        "large-module"
      ],
      "complexity": "complex",
      "filePath": "tools/real-transaction-smoke.mjs",
      "lineRange": [
        1,
        258
      ]
    },
    {
      "id": "function:tools/real-transaction-smoke.mjs:parseCredentialLine",
      "type": "function",
      "name": "parseCredentialLine",
      "summary": "Function parseCredentialLine in real-transaction-smoke.mjs.",
      "tags": [
        "function",
        "javascript"
      ],
      "complexity": "moderate",
      "filePath": "tools/real-transaction-smoke.mjs",
      "lineRange": [
        55,
        66
      ]
    },
    {
      "id": "function:tools/real-transaction-smoke.mjs:readCredentials",
      "type": "function",
      "name": "readCredentials",
      "summary": "Function readCredentials in real-transaction-smoke.mjs.",
      "tags": [
        "function",
        "javascript"
      ],
      "complexity": "moderate",
      "filePath": "tools/real-transaction-smoke.mjs",
      "lineRange": [
        68,
        80
      ]
    },
    {
      "id": "function:tools/real-transaction-smoke.mjs:callFunction",
      "type": "function",
      "name": "callFunction",
      "summary": "Function callFunction in real-transaction-smoke.mjs.",
      "tags": [
        "function",
        "javascript"
      ],
      "complexity": "moderate",
      "filePath": "tools/real-transaction-smoke.mjs",
      "lineRange": [
        89,
        111
      ]
    },
    {
      "id": "function:tools/real-transaction-smoke.mjs:login",
      "type": "function",
      "name": "login",
      "summary": "Function login in real-transaction-smoke.mjs.",
      "tags": [
        "function",
        "javascript"
      ],
      "complexity": "moderate",
      "filePath": "tools/real-transaction-smoke.mjs",
      "lineRange": [
        113,
        133
      ]
    },
    {
      "id": "function:tools/real-transaction-smoke.mjs:ticketPayload",
      "type": "function",
      "name": "ticketPayload",
      "summary": "Function ticketPayload in real-transaction-smoke.mjs.",
      "tags": [
        "function",
        "javascript"
      ],
      "complexity": "moderate",
      "filePath": "tools/real-transaction-smoke.mjs",
      "lineRange": [
        135,
        170
      ]
    },
    {
      "id": "function:tools/real-transaction-smoke.mjs:actionPayload",
      "type": "function",
      "name": "actionPayload",
      "summary": "Function actionPayload in real-transaction-smoke.mjs.",
      "tags": [
        "function",
        "javascript"
      ],
      "complexity": "moderate",
      "filePath": "tools/real-transaction-smoke.mjs",
      "lineRange": [
        172,
        185
      ]
    },
    {
      "id": "function:tools/real-transaction-smoke.mjs:runTicketFlow",
      "type": "function",
      "name": "runTicketFlow",
      "summary": "Function runTicketFlow in real-transaction-smoke.mjs.",
      "tags": [
        "function",
        "javascript"
      ],
      "complexity": "moderate",
      "filePath": "tools/real-transaction-smoke.mjs",
      "lineRange": [
        187,
        210
      ]
    },
    {
      "id": "function:tools/real-transaction-smoke.mjs:summarizeTicketCreate",
      "type": "function",
      "name": "summarizeTicketCreate",
      "summary": "Function summarizeTicketCreate in real-transaction-smoke.mjs.",
      "tags": [
        "function",
        "javascript"
      ],
      "complexity": "moderate",
      "filePath": "tools/real-transaction-smoke.mjs",
      "lineRange": [
        212,
        221
      ]
    },
    {
      "id": "function:tools/real-transaction-smoke.mjs:summarize",
      "type": "function",
      "name": "summarize",
      "summary": "Function summarize in real-transaction-smoke.mjs.",
      "tags": [
        "function",
        "javascript"
      ],
      "complexity": "moderate",
      "filePath": "tools/real-transaction-smoke.mjs",
      "lineRange": [
        223,
        233
      ]
    },
    {
      "id": "file:tools/results-monitor.mjs",
      "type": "file",
      "name": "results-monitor.mjs",
      "summary": "Source file tools/results-monitor.mjs containing 4 function(s).",
      "tags": [
        "code",
        "results"
      ],
      "complexity": "moderate",
      "filePath": "tools/results-monitor.mjs",
      "lineRange": [
        1,
        66
      ]
    },
    {
      "id": "function:tools/results-monitor.mjs:toDrDate",
      "type": "function",
      "name": "toDrDate",
      "summary": "Function toDrDate in results-monitor.mjs.",
      "tags": [
        "function",
        "javascript"
      ],
      "complexity": "moderate",
      "filePath": "tools/results-monitor.mjs",
      "lineRange": [
        6,
        14
      ]
    },
    {
      "id": "function:tools/results-monitor.mjs:fetchJson",
      "type": "function",
      "name": "fetchJson",
      "summary": "Function fetchJson in results-monitor.mjs.",
      "tags": [
        "function",
        "javascript"
      ],
      "complexity": "moderate",
      "filePath": "tools/results-monitor.mjs",
      "lineRange": [
        16,
        31
      ]
    },
    {
      "id": "function:tools/results-monitor.mjs:buildReport",
      "type": "function",
      "name": "buildReport",
      "summary": "Function buildReport in results-monitor.mjs.",
      "tags": [
        "function",
        "javascript"
      ],
      "complexity": "moderate",
      "filePath": "tools/results-monitor.mjs",
      "lineRange": [
        37,
        57
      ]
    },
    {
      "id": "file:tools/verify-pick-result-gate.mjs",
      "type": "file",
      "name": "verify-pick-result-gate.mjs",
      "summary": "Source file tools/verify-pick-result-gate.mjs containing 10 function(s).",
      "tags": [
        "code",
        "results"
      ],
      "complexity": "complex",
      "filePath": "tools/verify-pick-result-gate.mjs",
      "lineRange": [
        1,
        299
      ]
    },
    {
      "id": "function:tools/verify-pick-result-gate.mjs:zonedTimeToUtc",
      "type": "function",
      "name": "zonedTimeToUtc",
      "summary": "Function zonedTimeToUtc in verify-pick-result-gate.mjs.",
      "tags": [
        "function",
        "javascript"
      ],
      "complexity": "moderate",
      "filePath": "tools/verify-pick-result-gate.mjs",
      "lineRange": [
        113,
        133
      ]
    },
    {
      "id": "function:tools/verify-pick-result-gate.mjs:resolvePeriod",
      "type": "function",
      "name": "resolvePeriod",
      "summary": "Function resolvePeriod in verify-pick-result-gate.mjs.",
      "tags": [
        "function",
        "javascript"
      ],
      "complexity": "moderate",
      "filePath": "tools/verify-pick-result-gate.mjs",
      "lineRange": [
        135,
        144
      ]
    },
    {
      "id": "function:tools/verify-pick-result-gate.mjs:drawUtc",
      "type": "function",
      "name": "drawUtc",
      "summary": "Function drawUtc in verify-pick-result-gate.mjs.",
      "tags": [
        "function",
        "javascript"
      ],
      "complexity": "moderate",
      "filePath": "tools/verify-pick-result-gate.mjs",
      "lineRange": [
        146,
        161
      ]
    },
    {
      "id": "function:tools/verify-pick-result-gate.mjs:suppressEarly",
      "type": "function",
      "name": "suppressEarly",
      "summary": "Function suppressEarly in verify-pick-result-gate.mjs.",
      "tags": [
        "function",
        "javascript"
      ],
      "complexity": "moderate",
      "filePath": "tools/verify-pick-result-gate.mjs",
      "lineRange": [
        163,
        175
      ]
    }
  ],
  "edges": [
    {
      "source": "file:tools/real-transaction-smoke.mjs",
      "target": "function:tools/real-transaction-smoke.mjs:parseCredentialLine",
      "type": "contains",
      "direction": "forward",
      "weight": 1,
      "description": "real-transaction-smoke.mjs contains parseCredentialLine"
    },
    {
      "source": "file:tools/real-transaction-smoke.mjs",
      "target": "function:tools/real-transaction-smoke.mjs:readCredentials",
      "type": "contains",
      "direction": "forward",
      "weight": 1,
      "description": "real-transaction-smoke.mjs contains readCredentials"
    },
    {
      "source": "file:tools/real-transaction-smoke.mjs",
      "target": "function:tools/real-transaction-smoke.mjs:callFunction",
      "type": "contains",
      "direction": "forward",
      "weight": 1,
      "description": "real-transaction-smoke.mjs contains callFunction"
    },
    {
      "source": "file:tools/real-transaction-smoke.mjs",
      "target": "function:tools/real-transaction-smoke.mjs:login",
      "type": "contains",
      "direction": "forward",
      "weight": 1,
      "description": "real-transaction-smoke.mjs contains login"
    },
    {
      "source": "file:tools/real-transaction-smoke.mjs",
      "target": "function:tools/real-transaction-smoke.mjs:ticketPayload",
      "type": "contains",
      "direction": "forward",
      "weight": 1,
      "description": "real-transaction-smoke.mjs contains ticketPayload"
    },
    {
      "source": "file:tools/real-transaction-smoke.mjs",
      "target": "function:tools/real-transaction-smoke.mjs:actionPayload",
      "type": "contains",
      "direction": "forward",
      "weight": 1,
      "description": "real-transaction-smoke.mjs contains actionPayload"
    },
    {
      "source": "file:tools/real-transaction-smoke.mjs",
      "target": "function:tools/real-transaction-smoke.mjs:runTicketFlow",
      "type": "contains",
      "direction": "forward",
      "weight": 1,
      "description": "real-transaction-smoke.mjs contains runTicketFlow"
    },
    {
      "source": "file:tools/real-transaction-smoke.mjs",
      "target": "function:tools/real-transaction-smoke.mjs:summarizeTicketCreate",
      "type": "contains",
      "direction": "forward",
      "weight": 1,
      "description": "real-transaction-smoke.mjs contains summarizeTicketCreate"
    },
    {
      "source": "file:tools/real-transaction-smoke.mjs",
      "target": "function:tools/real-transaction-smoke.mjs:summarize",
      "type": "contains",
      "direction": "forward",
      "weight": 1,
      "description": "real-transaction-smoke.mjs contains summarize"
    },
    {
      "source": "file:tools/results-monitor.mjs",
      "target": "function:tools/results-monitor.mjs:toDrDate",
      "type": "contains",
      "direction": "forward",
      "weight": 1,
      "description": "results-monitor.mjs contains toDrDate"
    },
    {
      "source": "file:tools/results-monitor.mjs",
      "target": "function:tools/results-monitor.mjs:fetchJson",
      "type": "contains",
      "direction": "forward",
      "weight": 1,
      "description": "results-monitor.mjs contains fetchJson"
    },
    {
      "source": "file:tools/results-monitor.mjs",
      "target": "function:tools/results-monitor.mjs:buildReport",
      "type": "contains",
      "direction": "forward",
      "weight": 1,
      "description": "results-monitor.mjs contains buildReport"
    },
    {
      "source": "file:tools/verify-pick-result-gate.mjs",
      "target": "function:tools/verify-pick-result-gate.mjs:zonedTimeToUtc",
      "type": "contains",
      "direction": "forward",
      "weight": 1,
      "description": "verify-pick-result-gate.mjs contains zonedTimeToUtc"
    },
    {
      "source": "file:tools/verify-pick-result-gate.mjs",
      "target": "function:tools/verify-pick-result-gate.mjs:resolvePeriod",
      "type": "contains",
      "direction": "forward",
      "weight": 1,
      "description": "verify-pick-result-gate.mjs contains resolvePeriod"
    },
    {
      "source": "file:tools/verify-pick-result-gate.mjs",
      "target": "function:tools/verify-pick-result-gate.mjs:drawUtc",
      "type": "contains",
      "direction": "forward",
      "weight": 1,
      "description": "verify-pick-result-gate.mjs contains drawUtc"
    },
    {
      "source": "file:tools/verify-pick-result-gate.mjs",
      "target": "function:tools/verify-pick-result-gate.mjs:suppressEarly",
      "type": "contains",
      "direction": "forward",
      "weight": 1,
      "description": "verify-pick-result-gate.mjs contains suppressEarly"
    }
  ]
}